{
  "category": {
    "id": "cat-06a62187",
    "slug": "행택-쿠폰-안내장-청첩장-초대장-2187",
    "path": ["행택/쿠폰/안내장", "청첩장/초대장"],
    "displayName": "행택/쿠폰/안내장 > 청첩장/초대장",
    "productCount": 4,
    "keywords": ["행택", "쿠폰", "안내장", "청첩장", "초대장"],
    "summary": "행택/쿠폰/안내장 > 청첩장/초대장 · 4개 상품",
    "pricing": {
      "templated": 0,
      "quoted": 0
    }
  },
  "products": [
    {
      "productId": 40039,
      "name": "2단접지형",
      "slug": "2단접지형-40039",
      "categories": ["행택/쿠폰/안내장", "청첩장/초대장"],
      "keywords": [
        "행택",
        "쿠폰",
        "안내장",
        "청첩장",
        "초대장",
        "2단접지형",
        "ai",
        "eps",
        "jpg",
        "png",
        "cdr",
        "psd",
        "sit",
        "zip",
        "alz",
        "pdf"
      ],
      "useCases": [],
      "url": "https://devshop.wowpress.co.kr/prodt/40039",
      "fileTypes": ["AI", "EPS", "JPG", "PNG", "CDR", "PSD", "SIT", "ZIP", "ALZ", "PDF"],
      "delivery": {
        "cutoffTime": null,
        "prepayRequired": true,
        "group": {
          "id": 1,
          "name": "명함,스티커 묶음"
        },
        "regions": []
      },
      "orderQuantities": [
        {
          "type": "select",
          "values": [200, 300, 400, 600, 800, 900, 1000, 1200, 1500, 1800, 2100, 2400, 2700, 3000],
          "minimum": 200,
          "maximum": 3000,
          "interval": null,
          "materialPaperNo": 20369,
          "jobPresetNo": null,
          "sizeNo": null,
          "optionNo": null,
          "colorNo": null,
          "colorExtra": null
        },
        {
          "type": "select",
          "values": [
            200, 400, 600, 800, 1000, 1200, 1400, 1600, 1800, 2000, 2200, 2400, 2600, 2800, 3000
          ],
          "minimum": 200,
          "maximum": 3000,
          "interval": null,
          "materialPaperNo": 20450,
          "jobPresetNo": null,
          "sizeNo": null,
          "optionNo": null,
          "colorNo": null,
          "colorExtra": null
        },
        {
          "type": "select",
          "values": [500, 1000, 2000, 3000, 4000, 5000, 6000, 7000, 8000, 9000, 10000],
          "minimum": 500,
          "maximum": 10000,
          "interval": null,
          "materialPaperNo": 22904,
          "jobPresetNo": null,
          "sizeNo": null,
          "optionNo": null,
          "colorNo": null,
          "colorExtra": null
        },
        {
          "type": "select",
          "values": [500, 1000, 2000, 3000, 4000, 5000, 6000, 7000, 8000, 9000, 10000],
          "minimum": 500,
          "maximum": 10000,
          "interval": null,
          "materialPaperNo": 22907,
          "jobPresetNo": null,
          "sizeNo": null,
          "optionNo": null,
          "colorNo": null,
          "colorExtra": null
        }
      ],
      "coverTypes": [
        {
          "code": 0,
          "name": "통합",
          "pages": [
            {
              "code": 0,
              "name": "양면"
            }
          ],
          "pageConstraints": {
            "min": null,
            "max": null,
            "interval": null
          }
        }
      ],
      "detailFile": "../products/40039.json",
      "pricing": {
        "hasTemplate": false,
        "status": "requires-configuration",
        "sampleQuote": null,
        "error": null
      }
    },
    {
      "productId": 40108,
      "name": "엽서형",
      "slug": "엽서형-40108",
      "categories": ["행택/쿠폰/안내장", "청첩장/초대장"],
      "keywords": [
        "행택",
        "쿠폰",
        "안내장",
        "청첩장",
        "초대장",
        "엽서형",
        "ai",
        "eps",
        "jpg",
        "png",
        "cdr",
        "psd",
        "sit",
        "zip",
        "alz",
        "pdf"
      ],
      "useCases": ["stationery"],
      "url": "https://devshop.wowpress.co.kr/prodt/40108",
      "fileTypes": ["AI", "EPS", "JPG", "PNG", "CDR", "PSD", "SIT", "ZIP", "ALZ", "PDF"],
      "delivery": {
        "cutoffTime": null,
        "prepayRequired": true,
        "group": {
          "id": 1,
          "name": "명함,스티커 묶음"
        },
        "regions": []
      },
      "orderQuantities": [
        {
          "type": "select",
          "values": [200, 300, 400, 600, 800, 900, 1000, 1200, 1500, 1800, 2100, 2400, 2700, 3000],
          "minimum": 200,
          "maximum": 3000,
          "interval": null,
          "materialPaperNo": 20369,
          "jobPresetNo": null,
          "sizeNo": null,
          "optionNo": null,
          "colorNo": null,
          "colorExtra": null
        },
        {
          "type": "select",
          "values": [
            200, 400, 600, 800, 1000, 1200, 1400, 1600, 1800, 2000, 2200, 2400, 2600, 2800, 3000
          ],
          "minimum": 200,
          "maximum": 3000,
          "interval": null,
          "materialPaperNo": 20450,
          "jobPresetNo": null,
          "sizeNo": null,
          "optionNo": null,
          "colorNo": null,
          "colorExtra": null
        },
        {
          "type": "select",
          "values": [500, 1000, 2000, 3000, 4000, 5000, 6000, 7000, 8000, 9000, 10000],
          "minimum": 500,
          "maximum": 10000,
          "interval": null,
          "materialPaperNo": 22904,
          "jobPresetNo": null,
          "sizeNo": null,
          "optionNo": null,
          "colorNo": null,
          "colorExtra": null
        },
        {
          "type": "select",
          "values": [500, 1000, 2000, 3000, 4000, 5000, 6000, 7000, 8000, 9000, 10000],
          "minimum": 500,
          "maximum": 10000,
          "interval": null,
          "materialPaperNo": 22907,
          "jobPresetNo": null,
          "sizeNo": null,
          "optionNo": null,
          "colorNo": null,
          "colorExtra": null
        }
      ],
      "coverTypes": [
        {
          "code": 0,
          "name": "통합",
          "pages": [
            {
              "code": 0,
              "name": "양면"
            }
          ],
          "pageConstraints": {
            "min": null,
            "max": null,
            "interval": null
          }
        }
      ],
      "detailFile": "../products/40108.json",
      "pricing": {
        "hasTemplate": false,
        "status": "requires-configuration",
        "sampleQuote": null,
        "error": null
      }
    },
    {
      "productId": 40137,
      "name": "3단접지형",
      "slug": "3단접지형-40137",
      "categories": ["행택/쿠폰/안내장", "청첩장/초대장"],
      "keywords": [
        "행택",
        "쿠폰",
        "안내장",
        "청첩장",
        "초대장",
        "3단접지형",
        "ai",
        "eps",
        "jpg",
        "png",
        "cdr",
        "psd",
        "sit",
        "zip",
        "alz",
        "pdf"
      ],
      "useCases": [],
      "url": "https://devshop.wowpress.co.kr/prodt/40137",
      "fileTypes": ["AI", "EPS", "JPG", "PNG", "CDR", "PSD", "SIT", "ZIP", "ALZ", "PDF"],
      "delivery": {
        "cutoffTime": null,
        "prepayRequired": true,
        "group": {
          "id": 1,
          "name": "명함,스티커 묶음"
        },
        "regions": []
      },
      "orderQuantities": [
        {
          "type": "select",
          "values": [200, 300, 400, 600, 800, 900, 1000, 1200, 1500, 1800, 2100, 2400, 2700, 3000],
          "minimum": 200,
          "maximum": 3000,
          "interval": null,
          "materialPaperNo": 20369,
          "jobPresetNo": null,
          "sizeNo": null,
          "optionNo": null,
          "colorNo": null,
          "colorExtra": null
        },
        {
          "type": "select",
          "values": [
            200, 400, 600, 800, 1000, 1200, 1400, 1600, 1800, 2000, 2200, 2400, 2600, 2800, 3000
          ],
          "minimum": 200,
          "maximum": 3000,
          "interval": null,
          "materialPaperNo": 20450,
          "jobPresetNo": null,
          "sizeNo": null,
          "optionNo": null,
          "colorNo": null,
          "colorExtra": null
        },
        {
          "type": "select",
          "values": [500, 1000, 2000, 3000, 4000, 5000, 6000, 7000, 8000, 9000, 10000],
          "minimum": 500,
          "maximum": 10000,
          "interval": null,
          "materialPaperNo": 22904,
          "jobPresetNo": null,
          "sizeNo": null,
          "optionNo": null,
          "colorNo": null,
          "colorExtra": null
        },
        {
          "type": "select",
          "values": [500, 1000, 2000, 3000, 4000, 5000, 6000, 7000, 8000, 9000, 10000],
          "minimum": 500,
          "maximum": 10000,
          "interval": null,
          "materialPaperNo": 22907,
          "jobPresetNo": null,
          "sizeNo": null,
          "optionNo": null,
          "colorNo": null,
          "colorExtra": null
        }
      ],
      "coverTypes": [
        {
          "code": 0,
          "name": "통합",
          "pages": [
            {
              "code": 0,
              "name": "양면"
            }
          ],
          "pageConstraints": {
            "min": null,
            "max": null,
            "interval": null
          }
        }
      ],
      "detailFile": "../products/40137.json",
      "pricing": {
        "hasTemplate": false,
        "status": "requires-configuration",
        "sampleQuote": null,
        "error": null
      }
    },
    {
      "productId": 40607,
      "name": "식권",
      "slug": "식권-40607",
      "categories": ["행택/쿠폰/안내장", "청첩장/초대장"],
      "keywords": ["행택", "쿠폰", "안내장", "청첩장", "초대장", "식권", "ai", "eps", "pdf"],
      "useCases": [],
      "url": "https://devshop.wowpress.co.kr/prodt/40607",
      "fileTypes": ["AI", "EPS", "PDF"],
      "delivery": {
        "cutoffTime": null,
        "prepayRequired": true,
        "group": {
          "id": 68,
          "name": "식권 묶음"
        },
        "regions": []
      },
      "orderQuantities": [
        {
          "type": "select",
          "values": [100, 200, 300, 400, 500, 600, 700, 800, 900, 1000],
          "minimum": 100,
          "maximum": 1000,
          "interval": null,
          "materialPaperNo": null,
          "jobPresetNo": null,
          "sizeNo": null,
          "optionNo": null,
          "colorNo": null,
          "colorExtra": null
        }
      ],
      "coverTypes": [
        {
          "code": 0,
          "name": "통합",
          "pages": [
            {
              "code": 0,
              "name": "양면"
            }
          ],
          "pageConstraints": {
            "min": null,
            "max": null,
            "interval": null
          }
        }
      ],
      "detailFile": "../products/40607.json",
      "pricing": {
        "hasTemplate": false,
        "status": "requires-configuration",
        "sampleQuote": null,
        "error": null
      }
    }
  ]
}
